README.md
setup.py
proteome/__init__.py
proteome/env.py
proteome/logging.py
proteome/project.py
proteome/settings.py
proteome/state.py
proteome/version.py
proteome.egg-info/PKG-INFO
proteome.egg-info/SOURCES.txt
proteome.egg-info/dependency_links.txt
proteome.egg-info/requires.txt
proteome.egg-info/top_level.txt
proteome/components/__init__.py
proteome/components/config.py
proteome/components/core/__init__.py
proteome/components/core/main.py
proteome/components/core/message.py
proteome/components/ctags/__init__.py
proteome/components/ctags/main.py
proteome/components/ctags/messages.py
proteome/components/history/__init__.py
proteome/components/history/data.py
proteome/components/history/main.py
proteome/components/history/messages.py
proteome/components/history/patch.py
proteome/components/history/process.py
proteome/components/unite/__init__.py
proteome/components/unite/data.py
proteome/components/unite/main.py
proteome/git/__init__.py
proteome/git/process.py
proteome/git/repo.py
proteome/test/__init__.py
proteome/test/spec.py