Metadata-Version: 1.0
Name: proteome
Version: 11.4.3
Summary: project management for neovim
Home-page: https://github.com/tek/proteome
Author: Torsten Schmits
Author-email: torstenschmits@gmail.com
License: MIT
Platform: UNKNOWN
